Lab1_slave.sv
// Модуль "СЛЕЙВ"
module slave
#(
  parameter number_in_group_ADDR = 4'h0,  // адрес регистра, где хранится номер студента в группе
  parameter data_ADDR = 4'h4,             // адрес регистра, где хранится дата дд.мм.гг
  parameter surname_ADDR = 4'h8,          // адрес регистра, где хранится первые 4 буквы фамилии
  parameter name_ADDR = 4'hC              // адрес регистра, где хранится первые 4 буквы имени
)          

(
    input wire PWRITE,            // сигнал, выбирающий режим записи или чтения (1 - запись, 0 - чтение)
    input wire PCLK,              // сигнал синхронизации
    input wire PSEL,              // сигнал выбора переферии 
    input wire [31:0] PADDR,      // адрес регистра
    input wire [31:0] PWDATA,     // данные для записи в регистр
    input wire PENABLE,           // сигнал разрешения
    output reg [31:0] PRDATA = 0, // данные, прочитанные из регистра
    output reg PREADY = 0         // сигнал готовности (флаг того, что всё сделано успешно)
);

// Объявляем матрицу OP для хранения регистров
reg [31:0] OP [3:0];              // 0 - number_in_group, 1 - data, 2 - surname, 3 - name

// циклы записи и чтения интерфейса APB для переферийного устройства
// реагирует на входной сигнал и изменение переферийного устройства
always @(posedge PSEL or posedge PCLK) 
begin

    // запись в регистры (выбрано переферийное устройство, сигнал записи, разрешена работа с устройством)
    if (PSEL && PWRITE && PENABLE)
     begin
        // ЗАПИСЬ информации в отведённые ячейки
        case(PADDR)
         number_in_group_ADDR: OP[0] <= PWDATA; // запись по адресу регистра номера человека в группе
         data_ADDR: OP[1] <= PWDATA;            // запись по адресу регистра даты
         surname_ADDR: OP[2] <= PWDATA;         // запись по адресу регистра фамилии
         name_ADDR: OP[3] <= PWDATA;            // запись по адресу регистра имени
        endcase

        PRDATA <=0;                             // записанных данных нет
        PREADY <= 1'd1;                         // устанавливаем флаг заверешения операции
    end

    // ЧТЕНИЕ из регистров (выбрано переферийное устройство, подан сигнал чтения, разрешена работа)
    else if (PSEL && !PWRITE && PENABLE)
    begin
        // чтение информации из отведённых ячеек
        case(PADDR)
         number_in_group_ADDR: PRDATA <= OP[0];  // чтение по адресу номера человека в группе
         data_ADDR: PRDATA <= OP[1];             // чтение по адресу регистра даты
         surname_ADDR: PRDATA <= OP[2];          // чтение по адресу регистра фамилии
         name_ADDR: PRDATA <= OP[3];             // чтение по адресу регистра имени
        endcase

        PREADY <= 1'd1;                          // устанавливаем флаг заверешения операции
    end
   
   // сбрасываем PREADY после выполнения записи или чтения
   if (PREADY)
    begin
      PREADY <= !PREADY;
    end
end

endmodule

Lab1_master.sv
// модуль "МАСТЕР"
module master
(
    input wire PCLK,                     // сигнал синхронизации
    input wire PWRITE_MASTER,            // сигнал, выбирающий режим записи или чтения (1 - запись, 0 - чтение)
    input wire [31:0] PADDR_MASTER,      // адрес регистра
    input wire [31:0] PWDATA_MASTER,     // данные для записи в регистр
    input wire PRESET,                   // сигнал сброса
    input wire PREADY,                   // сигнал готовности (флаг того, что всё сделано успешно)
    input  wire [31:0] PRDATA,           // данные, прочитанные из слейва
    output reg PWRITE,                   // сигнал записи или чтения на вход слейва
    output reg PSEL = 0,                 // сигнал выбора переферии
    output reg [31:0] PRDATA_MASTER = 0, // данные, прочитанные из слейва
    output reg PENABLE = 0,              // сигнал разрешения, формирующийся в мастер APB 
    output reg [31:0] PADDR = 0,         // адрес, который мы будем передавать в слейв
    output reg [31:0] PWDATA             // данные, которые будут передаваться в слейв
);

// запись данных в шину APB
function void apb_write(input  [31:0] inp_addr,        // адрес для записи
                        input  [31:0] inp_data);       // данные для записи
begin
  PADDR = inp_addr;           // передаем адрес на входе мастера в слейв
  PWDATA = inp_data;          // передаём данные в слейв
  PWRITE = 1'd1;              // устанавливаем сигнал на запись
  PSEL = 1'd1;                // выбрано переферийное устройство для записи
  PENABLE = 1'd1;             // разрешаем запись через шину APB

  // когда слейв успешно записал передаваемые данные
  if(PREADY)
   begin
     PSEL = !PSEL;            // убираем переферийное устройство
     PENABLE = !PENABLE;      // запрет на продолжение дальнейших действий
   end
end
endfunction

//функция чтения из слейва
function void apb_read(input [31:0] inp_addr);
begin
  // операция не завершена
  if(!PREADY)
  begin
    PADDR = inp_addr;  // передаем адрес, откуда читаем на входе мастера в слейв
    PWRITE = 1'd0;     // устанавливаем сигнал чтения
    PSEL = 1'd1;       // выбрано переферийное устройство для чтения
    PENABLE = 1'd1;    // разрешаем чтение
  end
  
  // когда слейв завершил операцию чтения
  if(PREADY)
   begin
     PSEL = !PSEL;        // убираем переферийное устройство
     PENABLE = !PENABLE;  // запрет на продолжение дальнейших действий
   end
end
endfunction

// циклы записи и чтения интерфейса APB
always @(posedge PCLK or posedge PRESET) 
begin 
    // сигнал сброса равен 0 - сброс есть. Все выходные регистры сбрасываются
    if (!PRESET) 
    begin
      PADDR <= 32'b0;
      PWDATA <= 32'b0;
      PWRITE <= 1'b0;
      PSEL <= 1'b0;
      PENABLE <= 1'b0;
      PRDATA_MASTER <= 1'b0;
   end
   
   // сигнал сброса отсутствует
   else 
   begin
      if (!PWRITE_MASTER)         // чтение из регистров 
      begin
          apb_read(PADDR_MASTER); // вызов фунции чтения
      end
      else if (PWRITE_MASTER)     // запись в регистры
      begin
          apb_write(PADDR_MASTER, PWDATA_MASTER);
          PRDATA_MASTER <= 1'b0;
      end
   end
end


always @(posedge PREADY)
begin
  if (!PWRITE_MASTER)        // чтение из регистров 
    begin
     PRDATA_MASTER <=PRDATA; // вызов фунции чтения
    end
end
endmodule

Lab1_tb.sv
// модуль ТЕСТБЕНЧ
`include "Lab1_master.sv"      // подключаем файл МАСТЕРА
`include "Lab1_slave.sv"       // подключаем файл СЛЕЙВА


module Lab1_tb
#(
  parameter number_in_group_ADDR = 0,  // адрес регистра, где хранится номер студента в группе
  parameter data_ADDR = 4,             // адрес регистра, где хранится дата дд.мм.гг
  parameter surname_ADDR = 8,          // адрес регистра, где хранится первые 4 буквы фамилии
  parameter name_ADDR = 4'hC           // адрес регистра, где хранится первые 4 буквы имени
);

reg PCLK = 0;                  // сигнал синхронизации
reg PWRITE_MASTER = 0;         // сигнал, выбирающий режим записи или чтения (1 - запись, 0 - чтение)
wire PSEL;                     // сигнал выбора периферии 
reg [31:0] PADDR_MASTER = 0;   // Адрес регистра
reg [31:0] PWDATA_MASTER = 0;  // Данные для записи в регистр
wire [31:0] PRDATA_MASTER;     // Данные, прочитанные из слейва
wire PENABLE;                  // сигнал разрешения, формирующийся в мастер APB
reg PRESET = 0;                // сигнал сброса
wire PREADY;                   // сигнал готовности (флаг того, что всё сделано успешно)
wire [31:0] PADDR;             // адрес, который мы будем передавать в слейв
wire [31:0] PWDATA;            // данные, которые будут передаваться в слейв
wire [31:0] PRDATA ;           // данные, прочтённые с слейва
wire PWRITE;                   // сигнал записи или чтения на вход слейва

// создание экземпляра мастера
master Lab1_master_1 (
    .PCLK(PCLK),
    .PWRITE_MASTER(PWRITE_MASTER),
    .PSEL(PSEL),
    .PADDR_MASTER(PADDR_MASTER),
    .PWDATA_MASTER(PWDATA_MASTER),
    .PRDATA_MASTER(PRDATA_MASTER),
    .PENABLE(PENABLE),
    .PRESET(PRESET),
    .PREADY(PREADY),
    .PADDR(PADDR),
    .PWDATA(PWDATA),
    .PRDATA(PRDATA),
    .PWRITE(PWRITE)
);

// создание экземпляра слейва
slave Lab1_slave_1 (
    .PWRITE(PWRITE),
    .PSEL(PSEL),
    .PADDR(PADDR),
    .PWDATA(PWDATA),
    .PRDATA(PRDATA),
    .PENABLE(PENABLE),
    .PREADY(PREADY),
    .PCLK(PCLK)
);

// Объявление задачи для записи данных в регистр
task write_data;
  input reg [31:0] DATA;  // данные для записи
  input reg[31:0] ADDR;   // адрес регистра
  begin

    // Непосредственно операция записи
    PWRITE_MASTER = 1;              // выбираем запись
    PWDATA_MASTER = DATA;           // в данные для записи записываем свое значение
    PADDR_MASTER = ADDR;            // выбираем адрес регистра
  end
endtask

// объявление задачи для чтения данных из регистра
task read_data;
  input reg[31:0] ADDR;
  begin

    // Непосредственно операция чтения
    PWRITE_MASTER = 0;               // выбираем чтение
    PADDR_MASTER = ADDR;             // выбираем адрес для чтения
  end
endtask


initial begin
PCLK = 0;                            // устанавливаем начальное значение тактового сигнала
// сброс output регистров
PRESET = 0;
@(posedge PCLK);
PRESET = 1;
//ЗАПИСЬ
// записываем свой номер в группе
write_data(3, number_in_group_ADDR);
@(posedge PCLK);
@(posedge PCLK);
$display("Writing into address 0x%h record %h", PADDR, PWDATA);

// записываем сегодняшнюю дату
write_data(32'h10112023, data_ADDR);
@(posedge PCLK);
@(posedge PCLK);
$display("Writing into address 0x%h record %h", PADDR, PWDATA);

// записываем четыре первых буквы фамилии в формате ASCII 
write_data(32'h56494B55, surname_ADDR);
@(posedge PCLK);
@(posedge PCLK);
$display("Writing into address 0x%h record %h", PADDR, PWDATA);

// записываем четыре первые буквы имени в формате ASCII 
write_data(32'h444D4954, name_ADDR);
@(posedge PCLK);
@(posedge PCLK);
$display("Writing into address 0x%h record %h", PADDR, PWDATA);


//ЧТЕНИЕ
// читаем записанный номер в группе
read_data(number_in_group_ADDR);
@(posedge PCLK);
@(posedge PCLK);
$display("Reading from address 0x%h record %h", PADDR, PRDATA);

// читаем записанную дату
read_data(data_ADDR);
@(posedge PCLK);
@(posedge PCLK);
$display("Reading from address 0x%h record %h", PADDR, PRDATA);

// читаем записанные первые четыре буквы фамилии в формате ASCII
read_data(surname_ADDR);
@(posedge PCLK);
$display("Reading from address 0x%h record %h", PADDR, PRDATA);

// читаем первые четыре буквы имени в формате ASCII
read_data(name_ADDR);
@(posedge PCLK);
@(posedge PCLK);
$display("Reading from address 0x%h record %h", PADDR, PRDATA);

// Заканчиваем симуляцию
$finish;
end

always #150 PCLK = ~PCLK; // генерация входного сигнала PCLK

// создание файла .vcd и вывести значения переменных волны для отображения в визуализаторе волн
initial begin
$dumpfile("Lab1_tb.vcd");  // создание файла для сохранения результатов симуляции
$dumpvars(0, Lab1_tb);     // установка переменных для сохранения в файле
$dumpvars;
end


endmodule

Lab1_tb.vcd
$date
	Thu Nov 09 18:51:41 2023
$end
$version
	Icarus Verilog
$end
$timescale
	1s
$end
$scope module Lab1_tb $end
$var wire 1 ! PWRITE $end
$var wire 32 " PWDATA [31:0] $end
$var wire 1 # PSEL $end
$var wire 1 $ PREADY $end
$var wire 32 % PRDATA_MASTER [31:0] $end
$var wire 32 & PRDATA [31:0] $end
$var wire 1 ' PENABLE $end
$var wire 32 ( PADDR [31:0] $end
$var reg 32 ) PADDR_MASTER [31:0] $end
$var reg 1 * PCLK $end
$var reg 1 + PRESET $end
$var reg 32 , PWDATA_MASTER [31:0] $end
$var reg 1 - PWRITE_MASTER $end
$scope module Lab1_master_1 $end
$var wire 32 . PADDR_MASTER [31:0] $end
$var wire 1 * PCLK $end
$var wire 1 + PRESET $end
$var wire 32 / PWDATA_MASTER [31:0] $end
$var wire 1 - PWRITE_MASTER $end
$var wire 1 $ PREADY $end
$var wire 32 0 PRDATA [31:0] $end
$var reg 32 1 PADDR [31:0] $end
$var reg 1 ' PENABLE $end
$var reg 32 2 PRDATA_MASTER [31:0] $end
$var reg 1 # PSEL $end
$var reg 32 3 PWDATA [31:0] $end
$var reg 1 ! PWRITE $end
$scope function apb_read $end
$var reg 32 4 inp_addr [31:0] $end
$upscope $end
$scope function apb_write $end
$var reg 32 5 inp_addr [31:0] $end
$var reg 32 6 inp_data [31:0] $end
$upscope $end
$upscope $end
$scope module Lab1_slave_1 $end
$var wire 32 7 PADDR [31:0] $end
$var wire 1 * PCLK $end
$var wire 1 ' PENABLE $end
$var wire 1 # PSEL $end
$var wire 32 8 PWDATA [31:0] $end
$var wire 1 ! PWRITE $end
$var reg 32 9 PRDATA [31:0] $end
$var reg 1 $ PREADY $end
$upscope $end
$scope task read_data $end
$var reg 32 : ADDR [31:0] $end
$upscope $end
$scope task write_data $end
$var reg 32 ; ADDR [31:0] $end
$var reg 32 < DATA [31:0] $end
$upscope $end
$upscope $end
$scope module Lab1_tb $end
$scope module Lab1_master_1 $end
$scope function apb_read $end
$upscope $end
$scope function apb_write $end
$upscope $end
$upscope $end
$scope module Lab1_slave_1 $end
$upscope $end
$scope task read_data $end
$upscope $end
$scope task write_data $end
$upscope $end
$upscope $end
$enddefinitions $end
#0
$dumpvars
bx <
bx ;
bx :
b0 9
bx 8
b0 7
bx 6
bx 5
bx 4
bx 3
b0 2
b0 1
b0 0
b0 /
b0 .
0-
b0 ,
0+
0*
b0 )
b0 (
0'
b0 &
b0 %
0$
0#
bx "
x!
$end
#150
1$
1'
1#
1!
b11 "
b11 3
b11 8
b11 6
b0 5
b11 ,
b11 /
1-
b0 ;
b11 <
1+
1*
#300
0*
#450
0$
0'
0#
1*
#600
0*
#750
1$
1'
1#
b1000000100010010000000100011 "
b1000000100010010000000100011 3
b1000000100010010000000100011 8
b100 (
b100 1
b100 7
b1000000100010010000000100011 6
b100 5
b100 )
b100 .
b1000000100010010000000100011 ,
b1000000100010010000000100011 /
b100 ;
b1000000100010010000000100011 <
1*
#900
0*
#1050
0$
0'
0#
1*
#1200
0*
#1350
1$
1'
1#
b1010110010010010100101101010101 "
b1010110010010010100101101010101 3
b1010110010010010100101101010101 8
b1000 (
b1000 1
b1000 7
b1010110010010010100101101010101 6
b1000 5
b1000 )
b1000 .
b1010110010010010100101101010101 ,
b1010110010010010100101101010101 /
b1000 ;
b1010110010010010100101101010101 <
1*
#1500
0*
#1650
0$
0'
0#
1*
#1800
0*
#1950
1$
1'
1#
b1000100010011010100100101010100 "
b1000100010011010100100101010100 3
b1000100010011010100100101010100 8
b1100 (
b1100 1
b1100 7
b1000100010011010100100101010100 6
b1100 5
b1100 )
b1100 .
b1000100010011010100100101010100 ,
b1000100010011010100100101010100 /
b1100 ;
b1000100010011010100100101010100 <
1*
#2100
0*
#2250
0$
0'
0#
1*
#2400
0*
#2550
b11 %
b11 2
1$
b11 &
b11 0
b11 9
1'
1#
0!
b0 (
b0 1
b0 7
b0 4
b0 )
b0 .
0-
b0 :
1*
#2700
0*
#2850
0$
0'
0#
1*
#3000
0*
#3150
b1000000100010010000000100011 %
b1000000100010010000000100011 2
1$
b1000000100010010000000100011 &
b1000000100010010000000100011 0
b1000000100010010000000100011 9
1'
1#
b100 (
b100 1
b100 7
b100 4
b100 )
b100 .
b100 :
1*
#3300
0*
#3450
0$
0'
0#
1*
#3600
0*
#3750
b1010110010010010100101101010101 %
b1010110010010010100101101010101 2
1$
b1010110010010010100101101010101 &
b1010110010010010100101101010101 0
b1010110010010010100101101010101 9
1'
1#
b1000 (
b1000 1
b1000 7
b1000 4
b1000 )
b1000 .
b1000 :
1*
#3900
0*
#4050
0$
0'
0#
b1100 4
b1100 )
b1100 .
b1100 :
1*
#4200
0*
#4350
b1000100010011010100100101010100 %
b1000100010011010100100101010100 2
1$
b1000100010011010100100101010100 &
b1000100010011010100100101010100 0
b1000100010011010100100101010100 9
1'
1#
b1100 (
b1100 1
b1100 7
1*
#4500
0*
#4650
0$
0'
0#
1*
